[
  {
    "_id": "RV20250313001",
    "student_id": "2024002",
    "discipline_record_id": "DR20250306001",
    "hours": 2,
    "service_date": "2025-03-13",
    "description": "参与了校园花园的除草和美化工作，协助园艺老师种植花卉，整理草坪。",
    "witness": "园艺老师",
    "review_status": "approved",
    "activity_name": "校园绿化美化活动",
    "activity_type": "校园服务",
    "location": "校园花园区域",
    "certificate_image": "https://example.com/cert1.jpg",
    "review_date": "2025-03-14",
    "reviewer": "班主任",
    "review_comments": "服务态度认真，完成质量良好。",
    "created_by": "系统管理员",
    "submit_by": "学生",
    "createdAt": 1740979200000,
    "updatedAt": 1741065600000
  },
  {
    "_id": "RV20250314001",
    "student_id": "2024005",
    "discipline_record_id": "DR20250306002",
    "hours": 3,
    "service_date": "2025-03-14",
    "description": "协助社区工作人员为老人打扫卫生、整理房间，陪老人聊天交流。",
    "witness": "社区工作人员",
    "review_status": "approved",
    "activity_name": "社区敬老服务",
    "activity_type": "社区服务",
    "location": "社区养老服务中心",
    "certificate_image": "https://example.com/cert2.jpg",
    "review_date": "2025-03-15",
    "reviewer": "班主任",
    "review_comments": "表现积极，获得老人好评。",
    "created_by": "系统管理员",
    "submit_by": "学生",
    "createdAt": 1741065600000,
    "updatedAt": 1741152000000
  },
  {
    "_id": "RV20250315001",
    "student_id": "2024003",
    "discipline_record_id": "DR20250306003",
    "hours": 2.5,
    "service_date": "2025-03-15",
    "description": "协助图书馆管理员整理图书上架，维护图书分类秩序，帮助同学查找书籍。",
    "witness": "图书馆管理员",
    "review_status": "pending",
    "activity_name": "图书馆整理服务",
    "activity_type": "校园服务",
    "location": "学校图书馆",
    "certificate_image": "https://example.com/cert3.jpg",
    "review_date": null,
    "reviewer": null,
    "review_comments": null,
    "created_by": "系统管理员",
    "submit_by": "学生",
    "createdAt": 1741152000000,
    "updatedAt": 1741152000000
  },
  {
    "_id": "RV20250316001",
    "student_id": "2024006",
    "discipline_record_id": "DR20250306004",
    "hours": 4,
    "service_date": "2025-03-16",
    "description": "清理教学楼周边垃圾，擦拭宣传栏，整理自行车停放区域。",
    "witness": "值班老师",
    "review_status": "approved",
    "activity_name": "校园环境清洁活动",
    "activity_type": "校园服务",
    "location": "教学楼周边区域",
    "certificate_image": "https://example.com/cert4.jpg",
    "review_date": "2025-03-17",
    "reviewer": "班主任",
    "review_comments": "工作认真负责，完成任务出色。",
    "created_by": "系统管理员",
    "submit_by": "学生",
    "createdAt": 1741238400000,
    "updatedAt": 1741324800000
  },
  {
    "_id": "RV20250317001",
    "student_id": "2024008",
    "discipline_record_id": "DR20250306005",
    "hours": 3.5,
    "service_date": "2025-03-17",
    "description": "参与学校组织的公益义卖活动，协助布置场地、推销商品、整理物资。",
    "witness": "活动组织者",
    "review_status": "approved",
    "activity_name": "公益义卖活动",
    "activity_type": "公益服务",
    "location": "学校操场",
    "certificate_image": "https://example.com/cert5.jpg",
    "review_date": "2025-03-18",
    "reviewer": "班主任",
    "review_comments": "积极参与，表现优秀。",
    "created_by": "系统管理员",
    "submit_by": "学生",
    "createdAt": 1741324800000,
    "updatedAt": 1741411200000
  },
  {
    "_id": "RV20250318001",
    "student_id": "2024001",
    "discipline_record_id": "DR20250306006",
    "hours": 2,
    "service_date": "2025-03-18",
    "description": "参与春季植树活动，挖坑、栽树、浇水，学习植树知识。",
    "witness": "绿化负责人",
    "review_status": "pending",
    "activity_name": "植树造林活动",
    "activity_type": "环保服务",
    "location": "校园绿化区",
    "certificate_image": "https://example.com/cert6.jpg",
    "review_date": null,
    "reviewer": null,
    "review_comments": null,
    "created_by": "系统管理员",
    "submit_by": "学生",
    "createdAt": 1741411200000,
    "updatedAt": 1741411200000
  },
  {
    "_id": "RV20250319001",
    "student_id": "2024002",
    "discipline_record_id": "DR20250306001",
    "hours": 1.5,
    "service_date": "2025-03-19",
    "description": "协助食堂工作人员维持就餐秩序，引导同学文明用餐，收拾餐桌。",
    "witness": "食堂管理员",
    "review_status": "approved",
    "activity_name": "食堂秩序维护",
    "activity_type": "校园服务",
    "location": "学校食堂",
    "certificate_image": "https://example.com/cert7.jpg",
    "review_date": "2025-03-20",
    "reviewer": "班主任",
    "review_comments": "服务意识强，表现良好。",
    "created_by": "系统管理员",
    "submit_by": "学生",
    "createdAt": 1741497600000,
    "updatedAt": 1741584000000
  },
  {
    "_id": "RV20250320001",
    "student_id": "2024007",
    "discipline_record_id": "DR20250306007",
    "hours": 3,
    "service_date": "2025-03-20",
    "description": "协助交警进行交通安全宣传，发放宣传资料，提醒行人注意安全。",
    "witness": "交警",
    "review_status": "approved",
    "activity_name": "交通安全宣传",
    "activity_type": "社区服务",
    "location": "社区主要路口",
    "certificate_image": "https://example.com/cert8.jpg",
    "review_date": "2025-03-21",
    "reviewer": "班主任",
    "review_comments": "认真负责，宣传效果好。",
    "created_by": "系统管理员",
    "submit_by": "学生",
    "createdAt": 1741584000000,
    "updatedAt": 1741670400000
  },
  {
    "_id": "RV20250321001",
    "student_id": "2024009",
    "discipline_record_id": "DR20250306008",
    "hours": 4,
    "service_date": "2025-03-21",
    "description": "参与爱心支教活动，为小学生辅导功课，组织趣味游戏活动。",
    "witness": "小学老师",
    "review_status": "approved",
    "activity_name": "爱心支教活动",
    "activity_type": "公益服务",
    "location": "附近小学",
    "certificate_image": "https://example.com/cert9.jpg",
    "review_date": "2025-03-22",
    "reviewer": "班主任",
    "review_comments": "富有爱心，教学能力出色。",
    "created_by": "系统管理员",
    "submit_by": "学生",
    "createdAt": 1741670400000,
    "updatedAt": 1741756800000
  },
  {
    "_id": "RV20250322001",
    "student_id": "2024005",
    "discipline_record_id": "DR20250306002",
    "hours": 2.5,
    "service_date": "2025-03-22",
    "description": "协助社区举办文化活动，布置场地、引导观众、维持秩序。",
    "witness": "社区管理员",
    "review_status": "pending",
    "activity_name": "社区文化活动",
    "activity_type": "社区服务",
    "location": "社区文化中心",
    "certificate_image": "https://example.com/cert10.jpg",
    "review_date": null,
    "reviewer": null,
    "review_comments": null,
    "created_by": "系统管理员",
    "submit_by": "学生",
    "createdAt": 1741756800000,
    "updatedAt": 1741756800000
  }
]